{
  "_colors": {
    "color": {
      "medium": "#000",
      "border": "#ccc",
      "secondary": "#888",
      "lightest": "#999",
      "dark": "#444",
      "darkest": "#333",
      "neutral": {
        "10": "#FFFFFF",
        "20": "#F9F8F6",
        "30": "#F3F1ED",
        "40": "#EDE9E3",
        "50": "#E7E2DA",
        "60": "#BFBAB4",
        "70": "#97928F",
        "80": "#6F6969",
        "90": "#474143"
      },
      "red": {
        "10": "#FFE3E3",
        "20": "#FFBDBD",
        "30": "#FF9B9B",
        "40": "#F86A6A",
        "50": "#EF4E4E",
        "60": "#E12D39",
        "70": "#CF1124",
        "80": "#AB091E",
        "90": "#8A041A"
      },
      "yellow": {
        "10": "#FFFBEA",
        "20": "#FFF3C4",
        "30": "#FCE588",
        "40": "#FADB5F",
        "50": "#F7C948",
        "60": "#F0B429",
        "70": "#DE911D",
        "80": "#CB6E17",
        "90": "#B44D12"
      },
      "green": {
        "10": "#C1F2C7",
        "20": "#91E697",
        "30": "#51CA58",
        "40": "#31B237",
        "50": "#18981D",
        "60": "#0F8613",
        "70": "#0E7817",
        "80": "#07600E",
        "90": "#014807"
      },
      "blue": {
        "10": "#E6F6FF",
        "20": "#BAE3FF",
        "30": "#7CC4FA",
        "40": "#47A3F3",
        "50": "#2186EB",
        "60": "#0967D2",
        "70": "#0552B5",
        "80": "#03449E",
        "90": "#01337D"
      },
      "cyan": {
        "10": "#BEF8FD",
        "20": "#87EAF2",
        "30": "#54D1DB",
        "40": "#38BEC9",
        "50": "#2CB1BC",
        "60": "#14919B",
        "70": "#0E7C86",
        "80": "#0A6C74",
        "90": "#044E54"
      },
      "classes": {
        "druid": {
          "10": "#FFE9D6",
          "20": "#FFCEA3",
          "30": "#FFB370",
          "40": "#FF973D",
          "50": "#FF7C0A",
          "60": "#E87008",
          "70": "#D16405",
          "80": "#BA5803",
          "90": "#A34C00"
        },
        "hunter": {
          "10": "#E8F3D8",
          "20": "#D9EBBF",
          "30": "#CAE4A6",
          "40": "#BADC8C",
          "50": "#ABD473",
          "60": "#98C061",
          "70": "#85AD4E",
          "80": "#71993C",
          "90": "#5E8529"
        },
        "mage": {
          "10": "#D1EFFA",
          "20": "#B7E6F8",
          "30": "#9DDEF5",
          "40": "#83D5F3",
          "50": "#69CCF0",
          "60": "#52B4D7",
          "70": "#3C9BBE",
          "80": "#2583A4",
          "90": "#0E6A8B"
        },
        "paladin": {
          "10": "#FDE3EE",
          "20": "#FBCDE1",
          "30": "#F9B8D4",
          "40": "#F7A2C7",
          "50": "#F58CBA",
          "60": "#ED6EA5",
          "70": "#E44F90",
          "80": "#DC317B",
          "90": "#D31266"
        },
        "priest": {
          "10": "#E7CCFF",
          "20": "#EDD9FF",
          "30": "#F3E6FF",
          "40": "#F9F2FF",
          "50": "#FFFFFF",
          "60": "#DCBFE6",
          "70": "#B980CC",
          "80": "#9640B3",
          "90": "#730099"
        },
        "rogue": {
          "10": "#FFFBC2",
          "20": "#FFFAAC",
          "30": "#FFF896",
          "40": "#FFF77F",
          "50": "#FFF569",
          "60": "#DFD64F",
          "70": "#C0B635",
          "80": "#A0971A",
          "90": "#807700"
        },
        "shaman": {
          "10": "#ADD6FF",
          "20": "#82BDF7",
          "30": "#57A3EF",
          "40": "#2B8AE6",
          "50": "#0070DE",
          "60": "#0063C5",
          "70": "#0057AC",
          "80": "#004A93",
          "90": "#003D7A"
        },
        "warlock": {
          "10": "#ADD6FF",
          "20": "#CDC5E6",
          "30": "#BAAFDD",
          "40": "#A798D3",
          "50": "#9482C9",
          "60": "#816FB6",
          "70": "#6E5CA3",
          "80": "#5A4990",
          "90": "#47367D"
        },
        "warrior": {
          "10": "#F1E6DA",
          "20": "#E7D4BF",
          "30": "#DCC1A4",
          "40": "#D2AF89",
          "50": "#C79C6E",
          "60": "#B2895E",
          "70": "#9D764D",
          "80": "#87633D",
          "90": "#72502C"
        }
      },
      "adventures": {
        "karazhan": { "50": "#E2B4DF" },
        "loe": { "50": "#14A9A1" },
        "bm": { "50": "#FA5210" },
        "naxx": { "50": "#B5dE3F" }
      },
      "expansions": {
        "tgt": { "50": "#C41F3B" },
        "gvg": { "50": "#14A9A1" },
        "ungoro": { "50": "#3D9E2C" },
        "msog": { "50": "#D2CAC5" },
        "wotog": { "50": "#9482C9" },
        "kotft": { "50": "#A5F2F3" },
        "kac": { "50": "#FFD989" }
      },
      "media": {
        "facebook": { "logo": "#FFFFFF", "background": "#3B5998" },
        "twitter": { "logo": "#55ACEE", "background": "#FFFFFF" },
        "youtube": { "logo": "#FFFFFF", "background": "#BB0000" },
        "reddit": { "logo": "#FFFFFF", "background": "#FF4006" },
        "battlenet": { "logo": "#00C0F6", "background": "#1E293F" },
        "twitch": { "logo": "#FFFFFF", "background": "#6441A4" }
      }
    }
  },
  "_spacing": {
    "padding": { "small": "10", "medium": "20", "large": "30" },
    "borderRadius": { "small": "5", "default": "10" }
  },
  "_typography": {
    "font": {
      "type": {
        "primary": "\"Nunito Sans\", \"Helvetica Neue\", Helvetica, Arial, sans-serif"
      },
      "weight": {
        "regular": "400",
        "bold": "700",
        "extrabold": "800",
        "black": "900"
      },
      "size": {
        "s1": "12px",
        "s2": "14px",
        "s3": "16px",
        "m1": "20px",
        "m2": "24px",
        "m3": "28px",
        "l1": "32px",
        "l2": "40px",
        "l3": "48px",
        "code": "90px"
      }
    }
  }
}
